veg2hab/__init__.py
veg2hab/__main__.py
veg2hab/access_db.py
veg2hab/bronnen.py
veg2hab/constants.py
veg2hab/criteria.py
veg2hab/definitietabel.py
veg2hab/enums.py
veg2hab/functionele_samenhang.py
veg2hab/habitat.py
veg2hab/io/arcgis.py
veg2hab/io/cli.py
veg2hab/io/common.py
veg2hab/main.py
veg2hab/mozaiek.py
veg2hab/package_data/FGR.json
veg2hab/package_data/Oudebossen.gpkg
veg2hab/package_data/opgeschoonde_definitietabel.xlsx
veg2hab/package_data/opgeschoonde_waswordt.xlsx
veg2hab/package_data/veg2hab.pyt
veg2hab/validation.py
veg2hab/vegetatietypen.py
veg2hab/vegkartering.py
veg2hab/vegtypeinfo.py
veg2hab/waswordtlijst.py
veg2hab-1.1.2.dist-info/LICENSE.md
veg2hab-1.1.2.dist-info/METADATA
veg2hab-1.1.2.dist-info/WHEEL
veg2hab-1.1.2.dist-info/entry_points.txt
veg2hab-1.1.2.dist-info/RECORD
