Metadata-Version: 2.1
Name: veg2hab
Version: 1.1.2
Summary: Package voor automatisch omzetten van vegetatiekarteringen naar habitatkaarten
License: LGPLv3
Author: Spheer.ai
Author-email: info@spheer.ai
Requires-Python: >=3.10,<4.0
Classifier: License :: OSI Approved :: GNU Lesser General Public License v3 (LGPLv3)
Classifier: License :: Other/Proprietary License
Classifier: Programming Language :: Python :: 3
Classifier: Programming Language :: Python :: 3.10
Classifier: Programming Language :: Python :: 3.11
Classifier: Programming Language :: Python :: 3.12
Classifier: Programming Language :: Python :: 3.13
Requires-Dist: click (>=8.1.7,<9.0.0)
Requires-Dist: fiona (>=1.9.0,<2.0.0)
Requires-Dist: geopandas (>=1.0.1,<2.0.0)
Requires-Dist: openpyxl (>=3.1.2,<4.0.0)
Requires-Dist: pandas (>=2.0.2,<3.0.0)
Requires-Dist: pydantic (>=2.4.2,<3.0.0)
Requires-Dist: pydantic-settings (>=2.2.1,<3.0.0)
Requires-Dist: pyodbc (>=5.0.1,<6.0.0)
Requires-Dist: shapely (>=2.0.5,<3.0.0)
Requires-Dist: xlrd (>=2.0.1,<3.0.0)
